Workbook
Name Investiment_Suggestion: Planilha1!$D$17
Name investment: Planilha1!$D$20
Name Monthly_Fee: Planilha1!$D$22
Name Number_Of_Years: Planilha1!$D$21
Name Patrimony: Planilha1!$D$23
Name Portifolio_Income: Planilha1!$D$16
Name Salary: Planilha1!$D$15

Sheet Planilha1
B14: Configuration
B15: Salary | D15: 30000
B16: Portfolio yield | D16: 0.006
B17: Investment suggestion | D17: =D15*30% -> 9000
B19: Monthly Investiment
B20: How much to invest per month ? | D20: 9000
B21: For how many years ? | D21: 5
B22: Monthly return rate ? | D22: 0.0108
B23: Accumulated assets : | D23: =FV(Monthly_Fee,Number_Of_Years*12,investment*-1) -> 754236.17
B24: Monthly dividends : | D24: =D23*D22 -> 8145.7507
A25: 2
A26: 5 | B26: Scenarios | D26: Dividendos
A27: 10 | B27: How much in 2 years? | C27: =FV($D$22,$A25*12,$D$20*-1) -> 245077.77 | D27: =C27*Portifolio_Income -> 1470.4666
A28: 20 | B28: How much in 5 years? | C28: =FV($D$22,$A26*12,$D$20*-1) -> 754236.17 | D28: =C28*Portifolio_Income -> 4525.417
A29: 30 | B29: How much in 10 years? | C29: =FV($D$22,$A27*12,$D$20*-1) -> 2191119 | D29: =C29*Portifolio_Income -> 13146.714
B30: How much in 20 years? | C30: =FV($D$22,$A28*12,$D$20*-1) -> 10143441 | D30: =C30*Portifolio_Income -> 60860.646
B31: How much in 30 years? | C31: =FV($D$22,$A29*12,$D$20*-1) -> 39005143 | D31: =C31*Portifolio_Income -> 234030.86
B33: Profile | C33: Conservative
B34: Amount to be invested per month | C34: =investment -> 9000
B35: Type of FII | C35: Suggested Percentage | D35: Values
B36: Logistics | C36: =VLOOKUP($C$33&"-"&B36,Planilha2!B:E,4,FALSE) -> 0.2 | D36: =C36*$C$34 -> 1800
B37: Credit/Receivables | C37: =VLOOKUP($C$33&"-"&B37,Planilha2!B:E,4,FALSE) -> 0.15 | D37: =C37*$C$34 -> 1350
B38: Shopping Malls | C38: =VLOOKUP($C$33&"-"&B38,Planilha2!B:E,4,FALSE) -> 0.25 | D38: =C38*$C$34 -> 2250
B39: Office Buildings | C39: =VLOOKUP($C$33&"-"&B39,Planilha2!B:E,4,FALSE) -> 0.15 | D39: =C39*$C$34 -> 1350
B40: Hybrid | C40: =VLOOKUP($C$33&"-"&B40,Planilha2!B:E,4,FALSE) -> 0.1 | D40: =C40*$C$34 -> 900
B41: Hospitality | C41: =VLOOKUP($C$33&"-"&B41,Planilha2!B:E,4,FALSE) -> 0.15 | D41: =C41*$C$34 -> 1350
B42: Value | D42: =SUM(D36:D41) -> 9000

Sheet Planilha2
B4: Chave | C4: Profile | D4: Type OF fii | E4: %
B5: =C5&"-"&D5 -> Conservative-Logistics | C5: Conservative | D5: Logistics | E5: 0.2
B6: =C6&"-"&D6 -> Conservative-Credit/Receivables | C6: Conservative | D6: Credit/Receivables | E6: 0.15
B7: =C7&"-"&D7 -> Conservative-Shopping Malls | C7: Conservative | D7: Shopping Malls | E7: 0.25
B8: =C8&"-"&D8 -> Conservative-Office Buildings | C8: Conservative | D8: Office Buildings | E8: 0.15 | H8: Moderate-Credit/Receivables | I8: =VLOOKUP(H8,$B:$E,4,FALSE) -> 0.2
B9: =C9&"-"&D9 -> Conservative-Hybrid | C9: Conservative | D9: Hybrid | E9: 0.1
B10: =C10&"-"&D10 -> Conservative-Hospitality | C10: Conservative | D10: Hospitality | E10: 0.15
B11: =C11&"-"&D11 -> Moderate-Logistics | C11: Moderate | D11: Logistics | E11: 0.25
B12: =C12&"-"&D12 -> Moderate-Credit/Receivables | C12: Moderate | D12: Credit/Receivables | E12: 0.2
B13: =C13&"-"&D13 -> Moderate-Shopping Malls | C13: Moderate | D13: Shopping Malls | E13: 0.2
B14: =C14&"-"&D14 -> Moderate-Office Buildings | C14: Moderate | D14: Office Buildings | E14: 0.15
B15: =C15&"-"&D15 -> Moderate-Hybrid | C15: Moderate | D15: Hybrid | E15: 0.1
B16: =C16&"-"&D16 -> Moderate-Hospitality | C16: Moderate | D16: Hospitality | E16: 0.1
B17: =C17&"-"&D17 -> Aggressive-Logistics | C17: Aggressive | D17: Logistics | E17: 0.3
B18: =C18&"-"&D18 -> Aggressive-Credit/Receivables | C18: Aggressive | D18: Credit/Receivables | E18: 0.25
B19: =C19&"-"&D19 -> Aggressive-Shopping Malls | C19: Aggressive | D19: Shopping Malls | E19: 0.15
B20: =C20&"-"&D20 -> Aggressive-Office Buildings | C20: Aggressive | D20: Office Buildings | E20: 0.1
... B22: =C22&"-"&D22 -> Aggressive-Hospitality | C22: Aggressive | D22: Hospitality | E22: 0.1
